metricq/__init__.py
metricq/_protobuf_version.py
metricq/agent.py
metricq/client.py
metricq/connection_watchdog.py
metricq/data_client.py
metricq/datachunk_pb2.py
metricq/datachunk_pb2.pyi
metricq/drain.py
metricq/exceptions.py
metricq/history_client.py
metricq/history_pb2.py
metricq/history_pb2.pyi
metricq/interval_source.py
metricq/logging.py
metricq/py.typed
metricq/rpc.py
metricq/sink.py
metricq/source.py
metricq/source_metric.py
metricq/subscription.py
metricq/synchronous_source.py
metricq/version.py
metricq/cli/__init__.py
metricq/cli/decorator.py
metricq/cli/params.py
metricq/cli/syslog.py
metricq/pandas/__init__.py
metricq/pandas/pandas_history_client.py
metricq/timeseries/__init__.py
metricq/timeseries/extras.py
metricq/timeseries/time_aggregate.py
metricq/timeseries/time_value.py
metricq/timeseries/timedelta.py
metricq/timeseries/timestamp.py
metricq-5.4.0.dist-info/LICENSE
metricq-5.4.0.dist-info/METADATA
metricq-5.4.0.dist-info/WHEEL
metricq-5.4.0.dist-info/top_level.txt
metricq-5.4.0.dist-info/RECORD
