Metadata-Version: 2.1
Name: metricq
Version: 5.4.0
Summary: A highly-scalable, distributed metric data processing framework based on RabbitMQ
Home-page: https://github.com/metricq/metricq-python
Author: TU Dresden
License: BSD 3-clause "New" or "Revised License"
Classifier: License :: OSI Approved :: BSD License
Classifier: Programming Language :: Python :: 3
Requires-Python: >=3.10
License-File: LICENSE
Requires-Dist: aio-pika~=9.0
Requires-Dist: protobuf<3.13,>=3.12
Requires-Dist: Deprecated~=1.2.13
Requires-Dist: python-dateutil>=2.8.1,~=2.8
Requires-Dist: yarl
Requires-Dist: setuptools
Provides-Extra: examples
Requires-Dist: aiomonitor-ng; extra == "examples"
Requires-Dist: click; extra == "examples"
Requires-Dist: click-log; extra == "examples"
Provides-Extra: lint
Requires-Dist: black[jupyter]~=23.1.0; extra == "lint"
Requires-Dist: flake8; extra == "lint"
Requires-Dist: isort~=5.0; extra == "lint"
Requires-Dist: check-manifest; extra == "lint"
Requires-Dist: pre-commit; extra == "lint"
Provides-Extra: test
Requires-Dist: click; extra == "test"
Requires-Dist: click-log; extra == "test"
Requires-Dist: python-dotenv~=1.0.0; extra == "test"
Requires-Dist: pytest; extra == "test"
Requires-Dist: pytest-asyncio; extra == "test"
Requires-Dist: pytest-mock; extra == "test"
Provides-Extra: typing
Requires-Dist: mypy>=1.2.0; extra == "typing"
Requires-Dist: mypy-protobuf; extra == "typing"
Requires-Dist: types-Deprecated; extra == "typing"
Requires-Dist: types-setuptools; extra == "typing"
Requires-Dist: types-protobuf; extra == "typing"
Requires-Dist: types-python-dateutil; extra == "typing"
Requires-Dist: pandas-stubs~=2.0.1; extra == "typing"
Requires-Dist: uvloop; extra == "typing"
Requires-Dist: pandas~=2.2.0; extra == "typing"
Requires-Dist: aiomonitor-ng; extra == "typing"
Requires-Dist: click; extra == "typing"
Requires-Dist: click-log; extra == "typing"
Requires-Dist: click; extra == "typing"
Requires-Dist: click-log; extra == "typing"
Requires-Dist: python-dotenv~=1.0.0; extra == "typing"
Requires-Dist: pytest; extra == "typing"
Requires-Dist: pytest-asyncio; extra == "typing"
Requires-Dist: pytest-mock; extra == "typing"
Provides-Extra: docs
Requires-Dist: pandas~=2.2.0; extra == "docs"
Requires-Dist: sphinx~=6.1.3; extra == "docs"
Requires-Dist: sphinx_rtd_theme~=1.2.0; extra == "docs"
Requires-Dist: sphinx_autodoc_typehints~=1.22.0; extra == "docs"
Requires-Dist: sphinxcontrib-trio~=1.1.2; extra == "docs"
Requires-Dist: scanpydoc~=0.7.8; extra == "docs"
Provides-Extra: dev
Requires-Dist: click; extra == "dev"
Requires-Dist: click-log; extra == "dev"
Requires-Dist: python-dotenv~=1.0.0; extra == "dev"
Requires-Dist: pytest; extra == "dev"
Requires-Dist: pytest-asyncio; extra == "dev"
Requires-Dist: pytest-mock; extra == "dev"
Requires-Dist: black[jupyter]~=23.1.0; extra == "dev"
Requires-Dist: flake8; extra == "dev"
Requires-Dist: isort~=5.0; extra == "dev"
Requires-Dist: check-manifest; extra == "dev"
Requires-Dist: pre-commit; extra == "dev"
Requires-Dist: aiomonitor-ng; extra == "dev"
Requires-Dist: click; extra == "dev"
Requires-Dist: click-log; extra == "dev"
Requires-Dist: mypy>=1.2.0; extra == "dev"
Requires-Dist: mypy-protobuf; extra == "dev"
Requires-Dist: types-Deprecated; extra == "dev"
Requires-Dist: types-setuptools; extra == "dev"
Requires-Dist: types-protobuf; extra == "dev"
Requires-Dist: types-python-dateutil; extra == "dev"
Requires-Dist: pandas-stubs~=2.0.1; extra == "dev"
Requires-Dist: uvloop; extra == "dev"
Requires-Dist: pandas~=2.2.0; extra == "dev"
Requires-Dist: aiomonitor-ng; extra == "dev"
Requires-Dist: click; extra == "dev"
Requires-Dist: click-log; extra == "dev"
Requires-Dist: click; extra == "dev"
Requires-Dist: click-log; extra == "dev"
Requires-Dist: python-dotenv~=1.0.0; extra == "dev"
Requires-Dist: pytest; extra == "dev"
Requires-Dist: pytest-asyncio; extra == "dev"
Requires-Dist: pytest-mock; extra == "dev"
Requires-Dist: pandas~=2.2.0; extra == "dev"
Requires-Dist: sphinx~=6.1.3; extra == "dev"
Requires-Dist: sphinx_rtd_theme~=1.2.0; extra == "dev"
Requires-Dist: sphinx_autodoc_typehints~=1.22.0; extra == "dev"
Requires-Dist: sphinxcontrib-trio~=1.1.2; extra == "dev"
Requires-Dist: scanpydoc~=0.7.8; extra == "dev"
Requires-Dist: click; extra == "dev"
Requires-Dist: click-log; extra == "dev"
Requires-Dist: python-dotenv~=1.0.0; extra == "dev"
Requires-Dist: tox; extra == "dev"
Provides-Extra: pandas
Requires-Dist: pandas~=2.2.0; extra == "pandas"
Provides-Extra: cli
Requires-Dist: click; extra == "cli"
Requires-Dist: click-log; extra == "cli"
Requires-Dist: python-dotenv~=1.0.0; extra == "cli"
